aiospamc/__init__.py
aiospamc/cli.py
aiospamc/client.py
aiospamc/connections.py
aiospamc/exceptions.py
aiospamc/frontend.py
aiospamc/header_values.py
aiospamc/incremental_parser.py
aiospamc/requests.py
aiospamc/responses.py
aiospamc/user_warnings.py
aiospamc-1.2.0.dist-info/WHEEL
aiospamc-1.2.0.dist-info/entry_points.txt
aiospamc-1.2.0.dist-info/METADATA
aiospamc-1.2.0.dist-info/RECORD
