Metadata-Version: 2.4
Name: aiospamc
Version: 1.2.0
Summary: An asyncio-based library to communicate with SpamAssassin's SPAMD service.
Keywords: spam,spamc,spamassassin
Author: Michael Caley
Author-email: Michael Caley <mjcaley@darkarctic.com>
License-Expression: MIT
Classifier: Development Status :: 5 - Production/Stable
Classifier: Programming Language :: Python :: 3.10
Classifier: Programming Language :: Python :: 3.11
Classifier: Programming Language :: Python :: 3.12
Classifier: Programming Language :: Python :: 3.13
Classifier: Programming Language :: Python :: 3.14
Classifier: Intended Audience :: Developers
Classifier: Intended Audience :: System Administrators
Classifier: License :: OSI Approved :: MIT License
Classifier: Topic :: Communications :: Email :: Filters
Requires-Dist: certifi
Requires-Dist: loguru>=0.7
Requires-Dist: typer>=0.13,<0.17
Requires-Python: >=3.10, <4.0
Project-URL: documentation, https://aiospamc.readthedocs.io
Project-URL: homepage, https://github.com/mjcaley/aiospamc
Project-URL: repository, https://github.com/mjcaley/aiospamc
